forevd/__init__.py
forevd/__main__.py
forevd/apache/__init__.py
forevd/apache/httpd.conf
forevd/app.py
forevd/resources/__init__.py
forevd/resources/logging/__init__.py
forevd/resources/logging/cli.conf
forevd-0.3.1.dist-info/LICENSE
forevd-0.3.1.dist-info/METADATA
forevd-0.3.1.dist-info/WHEEL
forevd-0.3.1.dist-info/entry_points.txt
forevd-0.3.1.dist-info/RECORD
