Metadata-Version: 2.1
Name: forevd
Version: 0.3.1
Summary: Forward and reverse proxy using apache or nginx
License: LICENSE
Author: Erick Bourgeois
Author-email: erick@jeb.ca
Requires-Python: >=3.9,<4.0
Classifier: License :: Other/Proprietary License
Classifier: Programming Language :: Python :: 3
Classifier: Programming Language :: Python :: 3.9
Classifier: Programming Language :: Python :: 3.10
Classifier: Programming Language :: Python :: 3.11
Classifier: Programming Language :: Python :: 3.12
Classifier: Programming Language :: Python :: 3.13
Requires-Dist: Jinja2 (>=3.1.2)
Requires-Dist: fastapi (>=0.95.2)
Requires-Dist: firestone-lib (>=0.1.8)
Requires-Dist: requests (>=2.28.1)
Requires-Dist: uvicorn (>=0.22.0)
